{"last-year-high-resolution-score":null,"high-resolution-score":10.0,"revision":"ff9cb7162","calculated":true,"name":"osquery/tools/tests/test_example_queries.py","last-month":10,"last-month-details":{"name":"osquery/tools/tests/test_example_queries.py","score":10,"high-resolution-score":10.0,"unbiased-score":10.0,"details":{"cc-mean":1.5714285714285714,"main-body-cc":3,"lines-in-file":64,"complex-functions":[],"cc-median":1.0,"nested":{"contains-named-nested-functions":true,"nested-complexity-of-interest":[],"max-nested-in-global-scope":0,"max-nested-complexity-depth":0,"max-nested-complexity-depth-name":"<unknown>"},"excess-long-functions":[],"complex-conditionals":[],"longest-fn-loc-name":"ExampleQueryTests.setUp","n-functions":7,"active-code-size":38,"bumps":{},"longest-fn-loc":10,"cohesion":1,"clone-ratio":0,"fn-args":{"ctors-with-many-args":[],"max-args":1,"n-primitives":0,"fns-with-many-args":[],"max-ctor-args":0,"n-string-args":0,"mean-args":0.2857142857142857,"max-ctor-arg-name":"<unknown>","n-args":2,"max-arg-name":"ExampleQueryTests._execute"},"cc-max":3,"n-clones":0,"congestion":{"authors":1,"fractal-value":0.0},"median-fn-loc":3.0,"cc-max-name":"ExampleQueryTests._execute_set","cc-total":11},"revision":"c269bbeaf","date":"2015-07-13"},"last-year-details":{"details":{"lines-in-file":null},"revision":null,"date":null},"unbiased-score":10.0,"details":{"cc-mean":1.0,"main-body-cc":3,"lines-in-file":33,"social":{"owner":"Teddy Reed","ownership":1.0,"knowledge-loss":0.0},"complex-functions":[],"cc-median":1.0,"nested":{"contains-named-nested-functions":true,"nested-complexity-of-interest":[],"max-nested-in-global-scope":0,"max-nested-complexity-depth":0,"max-nested-complexity-depth-name":"<unknown>"},"code-comment-match":[{"n-matches":0,"pattern-name":"Detect TODOs"}],"excess-long-functions":[],"complex-conditionals":[],"longest-fn-loc-name":"ExampleQueryTests.test_cross_platform_queries","n-functions":3,"active-code-size":6,"bumps":{},"longest-fn-loc":2,"cohesion":1,"delta":{"active-code-delta":-32,"cc-total-delta":-8,"nested-depth-delta":0,"n-functions-delta":-4},"clone-ratio":0,"fn-args":{"ctors-with-many-args":[],"max-args":0,"n-primitives":0,"fns-with-many-args":[],"max-ctor-args":0,"n-string-args":0,"mean-args":0.0,"max-ctor-arg-name":"<unknown>","n-args":0,"max-arg-name":"ExampleQueryTests.test_cross_platform_queries"},"cc-max":1,"n-clones":0,"congestion":{"authors":1,"fractal-value":0.0},"median-fn-loc":2.0,"cc-max-name":"ExampleQueryTests.test_utility_queries","cc-total":3},"score":10,"last-month-high-resolution-score":10.0,"file-details":{"name":"osquery/tools/tests/test_example_queries.py","resolved":"/Users/andreaskarlsson/Documents/Exjobb/algorithm/test-oracle/repos/osquery/tools/tests/test_example_queries.py","repo-path":"/Users/andreaskarlsson/Documents/Exjobb/algorithm/test-oracle/repos/osquery","relative-name":"tools/tests/test_example_queries.py"},"last-year":0}