{"last-year-high-resolution-score":5.324143895474631,"high-resolution-score":4.61887103472117,"revision":"c7466e7894","calculated":true,"name":"salt/salt/modules/ssh.py","last-month":4,"last-month-details":{"name":"salt/salt/modules/ssh.py","score":4,"high-resolution-score":4.688431645926911,"unbiased-score":4.688431645926911,"details":{"cc-mean":8.96,"main-body-cc":0,"lines-in-file":812,"complex-functions":[{"name":"set_known_host","start-line":863,"end-line":972,"cc":28},{"name":"set_auth_key","start-line":631,"end-line":713,"cc":22},{"name":"user_keys","start-line":975,"end-line":1048,"cc":16},{"name":"host_keys","start-line":265,"end-line":308,"cc":12},{"name":"_expand_authorized_keys_path","start-line":81,"end-line":107,"cc":12},{"name":"set_auth_key_from_file","start-line":565,"end-line":628,"cc":11},{"name":"check_known_host","start-line":790,"end-line":828,"cc":10},{"name":"rm_auth_key_from_file","start-line":441,"end-line":497,"cc":10},{"name":"auth_keys","start-line":311,"end-line":349,"cc":10},{"name":"_get_known_hosts_file","start-line":241,"end-line":262,"cc":10},{"name":"_validate_keys","start-line":171,"end-line":220,"cc":10},{"name":"_replace_auth_key","start-line":124,"end-line":168,"cc":10},{"name":"rm_auth_key","start-line":500,"end-line":562,"cc":9}],"cc-median":9.0,"nested":{"contains-named-nested-functions":true,"nested-complexity-of-interest":[{"name":"user_keys","start-line":975,"end-line":1048,"nested-complexity":4}],"max-nested-in-global-scope":0,"max-nested-complexity-depth":4,"max-nested-complexity-depth-name":"user_keys"},"excess-long-functions":[{"name":"set_known_host","loc":85,"start-line":863,"end-line":972},{"name":"set_auth_key","loc":71,"start-line":631,"end-line":713}],"fns-with-duplicated-code":[{"name":"rm_auth_key_from_file","start-line":441,"end-line":497},{"name":"set_auth_key_from_file","start-line":565,"end-line":628}],"complex-conditionals":[],"longest-fn-loc-name":"set_known_host","n-functions":25,"active-code-size":788,"bumps":{"fns-with-small-bumps":6,"fns-with-large-bumps":0,"fns-with-severe-bumps":0,"worst-bump":{"bumps":4,"bump-locs":74,"name":"set_auth_key","start-line":631,"end-line":713},"bumps-by-severity":[{"bumps":4,"bump-locs":74,"name":"set_auth_key","start-line":631,"end-line":713},{"bumps":4,"bump-locs":63,"name":"user_keys","start-line":975,"end-line":1048},{"bumps":2,"bump-locs":29,"name":"host_keys","start-line":265,"end-line":308},{"bumps":2,"bump-locs":14,"name":"auth_keys","start-line":311,"end-line":349},{"bumps":2,"bump-locs":76,"name":"rm_auth_key","start-line":500,"end-line":562},{"bumps":2,"bump-locs":20,"name":"set_known_host","start-line":863,"end-line":972}]},"longest-fn-loc":85,"cohesion":3,"clone-ratio":0.08,"fn-args":{"ctors-with-many-args":[],"max-args":8,"n-primitives":0,"fns-with-many-args":[{"name":"_replace_auth_key","start-line":124,"end-line":168,"n-args":6},{"name":"check_key_file","start-line":352,"end-line":396,"n-args":5},{"name":"check_key","start-line":399,"end-line":438,"n-args":7},{"name":"rm_auth_key_from_file","start-line":441,"end-line":497,"n-args":5},{"name":"set_auth_key_from_file","start-line":565,"end-line":628,"n-args":5},{"name":"set_auth_key","start-line":631,"end-line":713,"n-args":7},{"name":"check_known_host","start-line":790,"end-line":828,"n-args":5},{"name":"set_known_host","start-line":863,"end-line":972,"n-args":8}],"max-ctor-args":0,"n-string-args":0,"mean-args":3.4,"max-ctor-arg-name":"<unknown>","n-args":85,"max-arg-name":"set_known_host"},"cc-max":28,"n-clones":2,"congestion":{"authors":3,"fractal-value":0.67},"median-fn-loc":27.0,"cc-max-name":"set_known_host","cc-total":224},"revision":"8766209ff7","date":"2015-05-15"},"last-year-details":{"details":{"lines-in-file":704},"revision":"f3830b1c44","date":"2014-07-26"},"unbiased-score":4.61887103472117,"details":{"cc-mean":9.0,"main-body-cc":0,"lines-in-file":828,"social":{"owner":"Thomas S Hatch","ownership":0.24,"knowledge-loss":0.0},"complex-functions":[{"name":"set_known_host","start-line":866,"end-line":986,"cc":34},{"name":"set_auth_key","start-line":632,"end-line":714,"cc":22},{"name":"user_keys","start-line":989,"end-line":1062,"cc":16},{"name":"host_keys","start-line":266,"end-line":309,"cc":12},{"name":"_expand_authorized_keys_path","start-line":82,"end-line":108,"cc":12},{"name":"set_auth_key_from_file","start-line":566,"end-line":629,"cc":11},{"name":"check_known_host","start-line":792,"end-line":830,"cc":10},{"name":"rm_auth_key_from_file","start-line":442,"end-line":498,"cc":10},{"name":"auth_keys","start-line":312,"end-line":350,"cc":10},{"name":"_get_known_hosts_file","start-line":242,"end-line":263,"cc":10},{"name":"_validate_keys","start-line":172,"end-line":221,"cc":10},{"name":"_replace_auth_key","start-line":125,"end-line":169,"cc":10},{"name":"rm_auth_key","start-line":501,"end-line":563,"cc":9}],"cc-median":8.5,"nested":{"contains-named-nested-functions":true,"nested-complexity-of-interest":[{"name":"user_keys","start-line":989,"end-line":1062,"nested-complexity":4}],"max-nested-in-global-scope":0,"max-nested-complexity-depth":4,"max-nested-complexity-depth-name":"user_keys"},"code-comment-match":[{"n-matches":4,"pattern-name":"Detect TODOs"}],"excess-long-functions":[{"name":"set_known_host","loc":93,"start-line":866,"end-line":986},{"name":"set_auth_key","loc":71,"start-line":632,"end-line":714}],"fns-with-duplicated-code":[{"name":"rm_auth_key_from_file","start-line":442,"end-line":498},{"name":"set_auth_key_from_file","start-line":566,"end-line":629}],"complex-conditionals":[{"name":"set_known_host","details":[{"start-line":892,"end-line":892,"branches":2}]}],"longest-fn-loc-name":"set_known_host","n-functions":26,"active-code-size":803,"bumps":{"fns-with-small-bumps":6,"fns-with-large-bumps":0,"fns-with-severe-bumps":0,"worst-bump":{"bumps":4,"bump-locs":74,"name":"set_auth_key","start-line":632,"end-line":714},"bumps-by-severity":[{"bumps":4,"bump-locs":74,"name":"set_auth_key","start-line":632,"end-line":714},{"bumps":4,"bump-locs":63,"name":"user_keys","start-line":989,"end-line":1062},{"bumps":2,"bump-locs":29,"name":"host_keys","start-line":266,"end-line":309},{"bumps":2,"bump-locs":14,"name":"auth_keys","start-line":312,"end-line":350},{"bumps":2,"bump-locs":76,"name":"rm_auth_key","start-line":501,"end-line":563},{"bumps":2,"bump-locs":20,"name":"set_known_host","start-line":866,"end-line":986}]},"longest-fn-loc":93,"cohesion":3,"delta":{"active-code-delta":15,"cc-total-delta":10,"nested-depth-delta":0,"n-functions-delta":1},"clone-ratio":0.07692307692307691,"fn-args":{"ctors-with-many-args":[],"max-args":8,"n-primitives":0,"fns-with-many-args":[{"name":"_replace_auth_key","start-line":125,"end-line":169,"n-args":6},{"name":"check_key_file","start-line":353,"end-line":397,"n-args":5},{"name":"check_key","start-line":400,"end-line":439,"n-args":7},{"name":"rm_auth_key_from_file","start-line":442,"end-line":498,"n-args":5},{"name":"set_auth_key_from_file","start-line":566,"end-line":629,"n-args":5},{"name":"set_auth_key","start-line":632,"end-line":714,"n-args":7},{"name":"check_known_host","start-line":792,"end-line":830,"n-args":6},{"name":"set_known_host","start-line":866,"end-line":986,"n-args":8}],"max-ctor-args":0,"n-string-args":0,"mean-args":3.4615384615384617,"max-ctor-arg-name":"<unknown>","n-args":90,"max-arg-name":"set_known_host"},"cc-max":34,"n-clones":2,"congestion":{"authors":1,"fractal-value":0.0},"median-fn-loc":26.0,"cc-max-name":"set_known_host","cc-total":234},"score":4,"last-month-high-resolution-score":4.688431645926911,"file-details":{"name":"salt/salt/modules/ssh.py","resolved":"/Users/andreaskarlsson/Documents/Exjobb/algorithm/test-oracle/repos/salt/salt/modules/ssh.py","repo-path":"/Users/andreaskarlsson/Documents/Exjobb/algorithm/test-oracle/repos/salt","relative-name":"salt/modules/ssh.py"},"last-year":5}