{"last-year-high-resolution-score":5.622110812702044,"high-resolution-score":3.8691749640839794,"revision":"6b2100a30b","calculated":true,"name":"salt/salt/client/ssh/__init__.py","last-month":3,"last-month-details":{"name":"salt/salt/client/ssh/__init__.py","score":3,"high-resolution-score":3.8801211686673933,"unbiased-score":3.8801211686673933,"details":{"cc-mean":7.925925925925926,"main-body-cc":3,"lines-in-file":1056,"complex-functions":[{"name":"Single.run_wfunc","start-line":745,"end-line":884,"cc":33},{"name":"SSH.handle_ssh","start-line":373,"end-line":447,"cc":23},{"name":"Single.cmd_block","start-line":977,"end-line":1056,"cc":21},{"name":"SSH.run","start-line":503,"end-line":584,"cc":18},{"name":"mod_data","start-line":1182,"end-line":1236,"cc":14},{"name":"SSH.__init__","start-line":160,"end-line":252,"cc":11},{"name":"Single.__init__","start-line":595,"end-line":675,"cc":10}],"cc-median":6.0,"nested":{"contains-named-nested-functions":true,"nested-complexity-of-interest":[{"name":"SSH.handle_ssh","start-line":373,"end-line":447,"nested-complexity":6},{"name":"mod_data","start-line":1182,"end-line":1236,"nested-complexity":6},{"name":"Single.cmd_block","start-line":977,"end-line":1056,"nested-complexity":4},{"name":"salt_refs","start-line":1165,"end-line":1179,"nested-complexity":4},{"name":"_convert_args","start-line":1262,"end-line":1276,"nested-complexity":4}],"max-nested-in-global-scope":0,"max-nested-complexity-depth":6,"max-nested-complexity-depth-name":"SSH.handle_ssh"},"excess-long-functions":[{"name":"Single.run_wfunc","loc":114,"start-line":745,"end-line":884},{"name":"SSH.__init__","loc":91,"start-line":160,"end-line":252},{"name":"Single.__init__","loc":76,"start-line":595,"end-line":675},{"name":"SSH.run","loc":73,"start-line":503,"end-line":584},{"name":"SSH.handle_ssh","loc":71,"start-line":373,"end-line":447}],"complex-conditionals":[],"longest-fn-loc-name":"Single.run_wfunc","n-functions":27,"active-code-size":964,"bumps":{"fns-with-small-bumps":7,"fns-with-large-bumps":0,"fns-with-severe-bumps":0,"worst-bump":{"bumps":4,"bump-locs":91,"name":"SSH.handle_ssh","start-line":373,"end-line":447},"bumps-by-severity":[{"bumps":4,"bump-locs":91,"name":"SSH.handle_ssh","start-line":373,"end-line":447},{"bumps":4,"bump-locs":72,"name":"Single.run_wfunc","start-line":745,"end-line":884},{"bumps":3,"bump-locs":52,"name":"Single.cmd_block","start-line":977,"end-line":1056},{"bumps":3,"bump-locs":28,"name":"mod_data","start-line":1182,"end-line":1236},{"bumps":2,"bump-locs":17,"name":"SSH.key_deploy","start-line":270,"end-line":291},{"bumps":2,"bump-locs":19,"name":"lowstate_file_refs","start-line":1142,"end-line":1162},{"bumps":2,"bump-locs":8,"name":"salt_refs","start-line":1165,"end-line":1179}]},"longest-fn-loc":114,"cohesion":6,"clone-ratio":0,"fn-args":{"ctors-with-many-args":[],"max-args":18,"n-primitives":0,"fns-with-many-args":[{"name":"SSH.handle_routine","start-line":338,"end-line":371,"n-args":5},{"name":"Single.__init__","start-line":595,"end-line":675,"n-args":18}],"max-ctor-args":0,"n-string-args":0,"mean-args":1.7777777777777777,"max-ctor-arg-name":"<unknown>","n-args":48,"max-arg-name":"Single.__init__"},"cc-max":33,"n-clones":0,"congestion":{"authors":1,"fractal-value":0.0},"median-fn-loc":21.0,"cc-max-name":"Single.run_wfunc","cc-total":214},"revision":"fc9267afa3","date":"2015-07-12"},"last-year-details":{"details":{"lines-in-file":830},"revision":"d805d7d1d7","date":"2014-08-15"},"unbiased-score":3.8691749640839794,"details":{"cc-mean":8.0,"main-body-cc":3,"lines-in-file":1062,"social":{"owner":"Thomas S Hatch","ownership":0.54,"knowledge-loss":0.0},"complex-functions":[{"name":"Single.run_wfunc","start-line":746,"end-line":885,"cc":33},{"name":"SSH.handle_ssh","start-line":373,"end-line":447,"cc":23},{"name":"Single.cmd_block","start-line":978,"end-line":1057,"cc":21},{"name":"SSH.run","start-line":503,"end-line":584,"cc":19},{"name":"mod_data","start-line":1188,"end-line":1242,"cc":14},{"name":"SSH.__init__","start-line":160,"end-line":252,"cc":11},{"name":"Single.__init__","start-line":595,"end-line":676,"cc":10}],"cc-median":6.0,"nested":{"contains-named-nested-functions":true,"nested-complexity-of-interest":[{"name":"SSH.handle_ssh","start-line":373,"end-line":447,"nested-complexity":6},{"name":"mod_data","start-line":1188,"end-line":1242,"nested-complexity":6},{"name":"Single.cmd_block","start-line":978,"end-line":1057,"nested-complexity":4},{"name":"salt_refs","start-line":1171,"end-line":1185,"nested-complexity":4},{"name":"_convert_args","start-line":1268,"end-line":1282,"nested-complexity":4}],"max-nested-in-global-scope":0,"max-nested-complexity-depth":6,"max-nested-complexity-depth-name":"SSH.handle_ssh"},"code-comment-match":[{"n-matches":3,"pattern-name":"Detect TODOs"}],"excess-long-functions":[{"name":"Single.run_wfunc","loc":114,"start-line":746,"end-line":885},{"name":"SSH.__init__","loc":91,"start-line":160,"end-line":252},{"name":"Single.__init__","loc":77,"start-line":595,"end-line":676},{"name":"SSH.run","loc":73,"start-line":503,"end-line":584},{"name":"SSH.handle_ssh","loc":71,"start-line":373,"end-line":447}],"complex-conditionals":[],"longest-fn-loc-name":"Single.run_wfunc","n-functions":27,"active-code-size":970,"bumps":{"fns-with-small-bumps":7,"fns-with-large-bumps":0,"fns-with-severe-bumps":0,"worst-bump":{"bumps":4,"bump-locs":91,"name":"SSH.handle_ssh","start-line":373,"end-line":447},"bumps-by-severity":[{"bumps":4,"bump-locs":91,"name":"SSH.handle_ssh","start-line":373,"end-line":447},{"bumps":4,"bump-locs":72,"name":"Single.run_wfunc","start-line":746,"end-line":885},{"bumps":3,"bump-locs":52,"name":"Single.cmd_block","start-line":978,"end-line":1057},{"bumps":3,"bump-locs":28,"name":"mod_data","start-line":1188,"end-line":1242},{"bumps":2,"bump-locs":17,"name":"SSH.key_deploy","start-line":270,"end-line":291},{"bumps":2,"bump-locs":19,"name":"lowstate_file_refs","start-line":1148,"end-line":1168},{"bumps":2,"bump-locs":8,"name":"salt_refs","start-line":1171,"end-line":1185}]},"longest-fn-loc":114,"cohesion":6,"delta":{"active-code-delta":6,"cc-total-delta":2,"nested-depth-delta":0,"n-functions-delta":0},"clone-ratio":0,"fn-args":{"ctors-with-many-args":[],"max-args":18,"n-primitives":0,"fns-with-many-args":[{"name":"SSH.handle_routine","start-line":338,"end-line":371,"n-args":5},{"name":"Single.__init__","start-line":595,"end-line":676,"n-args":18}],"max-ctor-args":0,"n-string-args":0,"mean-args":1.8518518518518519,"max-ctor-arg-name":"<unknown>","n-args":50,"max-arg-name":"Single.__init__"},"cc-max":33,"n-clones":0,"congestion":{"authors":3,"fractal-value":0.67},"median-fn-loc":21.0,"cc-max-name":"Single.run_wfunc","cc-total":216},"score":3,"last-month-high-resolution-score":3.8801211686673933,"file-details":{"name":"salt/salt/client/ssh/__init__.py","resolved":"/Users/andreaskarlsson/Documents/Exjobb/algorithm/test-oracle/repos/salt/salt/client/ssh/__init__.py","repo-path":"/Users/andreaskarlsson/Documents/Exjobb/algorithm/test-oracle/repos/salt","relative-name":"salt/client/ssh/__init__.py"},"last-year":5}