{"last-year-high-resolution-score":null,"high-resolution-score":9.387218218812514,"revision":"9cc897fd69","calculated":true,"name":"salt/tests/unit/modules/iptables_test.py","last-month":9,"last-month-details":{"name":"salt/tests/unit/modules/iptables_test.py","score":9,"high-resolution-score":9.387218218812514,"unbiased-score":9.387218218812514,"details":{"cc-mean":1.0,"main-body-cc":1,"lines-in-file":335,"complex-functions":[],"cc-median":1.0,"nested":{"contains-named-nested-functions":true,"nested-complexity-of-interest":[],"max-nested-in-global-scope":0,"max-nested-complexity-depth":0,"max-nested-complexity-depth-name":"<unknown>"},"excess-long-functions":[],"fns-with-duplicated-code":[{"name":"IptablesTestCase.test_get_saved_policy","start-line":166,"end-line":191},{"name":"IptablesTestCase.test_get_policy","start-line":195,"end-line":217},{"name":"IptablesTestCase.test_check_chain","start-line":311,"end-line":323},{"name":"IptablesTestCase.test_new_chain","start-line":327,"end-line":339},{"name":"IptablesTestCase.test_delete_chain","start-line":343,"end-line":355}],"complex-conditionals":[],"longest-fn-loc-name":"IptablesTestCase.test_build_rule","n-functions":16,"active-code-size":296,"bumps":{},"longest-fn-loc":64,"cohesion":1,"clone-ratio":0.3125,"fn-args":{"ctors-with-many-args":[],"max-args":0,"n-primitives":0,"fns-with-many-args":[],"max-ctor-args":0,"n-string-args":0,"mean-args":0.0,"max-ctor-arg-name":"<unknown>","n-args":0,"max-arg-name":"IptablesTestCase.test_version"},"cc-max":1,"n-clones":5,"congestion":{"authors":1,"fractal-value":0.0},"median-fn-loc":13.0,"cc-max-name":"IptablesTestCase.test_flush","cc-total":16},"revision":"9cc897fd69","date":"2015-07-13"},"last-year-details":{"details":{"lines-in-file":null},"revision":null,"date":null},"unbiased-score":9.387218218812514,"details":{"cc-mean":1.0,"main-body-cc":1,"lines-in-file":335,"social":{"owner":"Jayesh Kariya","ownership":0.75,"knowledge-loss":0.0},"complex-functions":[],"cc-median":1.0,"nested":{"contains-named-nested-functions":true,"nested-complexity-of-interest":[],"max-nested-in-global-scope":0,"max-nested-complexity-depth":0,"max-nested-complexity-depth-name":"<unknown>"},"code-comment-match":[{"n-matches":0,"pattern-name":"Detect TODOs"}],"excess-long-functions":[],"fns-with-duplicated-code":[{"name":"IptablesTestCase.test_get_saved_policy","start-line":166,"end-line":191},{"name":"IptablesTestCase.test_get_policy","start-line":195,"end-line":217},{"name":"IptablesTestCase.test_check_chain","start-line":311,"end-line":323},{"name":"IptablesTestCase.test_new_chain","start-line":327,"end-line":339},{"name":"IptablesTestCase.test_delete_chain","start-line":343,"end-line":355}],"complex-conditionals":[],"longest-fn-loc-name":"IptablesTestCase.test_build_rule","n-functions":16,"active-code-size":296,"bumps":{},"longest-fn-loc":64,"cohesion":1,"delta":{"active-code-delta":0,"cc-total-delta":0,"nested-depth-delta":0,"n-functions-delta":0},"clone-ratio":0.3125,"fn-args":{"ctors-with-many-args":[],"max-args":0,"n-primitives":0,"fns-with-many-args":[],"max-ctor-args":0,"n-string-args":0,"mean-args":0.0,"max-ctor-arg-name":"<unknown>","n-args":0,"max-arg-name":"IptablesTestCase.test_version"},"cc-max":1,"n-clones":5,"congestion":{"authors":0,"fractal-value":0.0},"median-fn-loc":13.0,"cc-max-name":"IptablesTestCase.test_flush","cc-total":16},"score":9,"last-month-high-resolution-score":9.387218218812514,"file-details":{"name":"salt/tests/unit/modules/iptables_test.py","resolved":"/Users/andreaskarlsson/Documents/Exjobb/algorithm/test-oracle/repos/salt/tests/unit/modules/iptables_test.py","repo-path":"/Users/andreaskarlsson/Documents/Exjobb/algorithm/test-oracle/repos/salt","relative-name":"tests/unit/modules/iptables_test.py"},"last-year":0}