{"last-year-high-resolution-score":null,"high-resolution-score":7.3098232073275575,"revision":"abfae94e1d","calculated":true,"name":"salt/salt/states/x509.py","last-month":7,"last-month-details":{"name":"salt/salt/states/x509.py","score":7,"high-resolution-score":7.3098232073275575,"unbiased-score":7.3098232073275575,"details":{"cc-mean":10.666666666666666,"main-body-cc":0,"lines-in-file":479,"complex-functions":[{"name":"certificate_managed","start-line":323,"end-line":459,"cc":22},{"name":"crl_managed","start-line":462,"end-line":579,"cc":12},{"name":"private_key_managed","start-line":187,"end-line":258,"cc":9}],"cc-median":8.5,"nested":{"contains-named-nested-functions":true,"nested-complexity-of-interest":[{"name":"_revoked_to_list","start-line":167,"end-line":184,"nested-complexity":5},{"name":"certificate_managed","start-line":323,"end-line":459,"nested-complexity":4}],"max-nested-in-global-scope":0,"max-nested-complexity-depth":5,"max-nested-complexity-depth-name":"_revoked_to_list"},"excess-long-functions":[{"name":"certificate_managed","loc":115,"start-line":323,"end-line":459},{"name":"crl_managed","loc":94,"start-line":462,"end-line":579}],"complex-conditionals":[{"name":"certificate_managed","details":[{"start-line":436,"end-line":438,"branches":2}]},{"name":"crl_managed","details":[{"start-line":555,"end-line":557,"branches":2}]}],"longest-fn-loc-name":"certificate_managed","n-functions":6,"active-code-size":361,"bumps":{"fns-with-small-bumps":1,"fns-with-large-bumps":0,"fns-with-severe-bumps":0,"worst-bump":{"bumps":2,"bump-locs":43,"name":"certificate_managed","start-line":323,"end-line":459},"bumps-by-severity":[{"bumps":2,"bump-locs":43,"name":"certificate_managed","start-line":323,"end-line":459}]},"longest-fn-loc":115,"cohesion":1,"clone-ratio":0,"fn-args":{"ctors-with-many-args":[],"max-args":8,"n-primitives":0,"fns-with-many-args":[{"name":"crl_managed","start-line":462,"end-line":579,"n-args":8}],"max-ctor-args":0,"n-string-args":0,"mean-args":3.8333333333333335,"max-ctor-arg-name":"<unknown>","n-args":23,"max-arg-name":"crl_managed"},"cc-max":22,"n-clones":0,"congestion":{"authors":1,"fractal-value":0.0},"median-fn-loc":52.0,"cc-max-name":"certificate_managed","cc-total":64},"revision":"abfae94e1d","date":"2015-07-08"},"last-year-details":{"details":{"lines-in-file":null},"revision":null,"date":null},"unbiased-score":7.3098232073275575,"details":{"cc-mean":10.666666666666666,"main-body-cc":0,"lines-in-file":479,"social":{"owner":"Clint Armstrong","ownership":0.99,"knowledge-loss":0.0},"complex-functions":[{"name":"certificate_managed","start-line":323,"end-line":459,"cc":22},{"name":"crl_managed","start-line":462,"end-line":579,"cc":12},{"name":"private_key_managed","start-line":187,"end-line":258,"cc":9}],"cc-median":8.5,"nested":{"contains-named-nested-functions":true,"nested-complexity-of-interest":[{"name":"_revoked_to_list","start-line":167,"end-line":184,"nested-complexity":5},{"name":"certificate_managed","start-line":323,"end-line":459,"nested-complexity":4}],"max-nested-in-global-scope":0,"max-nested-complexity-depth":5,"max-nested-complexity-depth-name":"_revoked_to_list"},"code-comment-match":[{"n-matches":0,"pattern-name":"Detect TODOs"}],"excess-long-functions":[{"name":"certificate_managed","loc":115,"start-line":323,"end-line":459},{"name":"crl_managed","loc":94,"start-line":462,"end-line":579}],"complex-conditionals":[{"name":"certificate_managed","details":[{"start-line":436,"end-line":438,"branches":2}]},{"name":"crl_managed","details":[{"start-line":555,"end-line":557,"branches":2}]}],"longest-fn-loc-name":"certificate_managed","n-functions":6,"active-code-size":361,"bumps":{"fns-with-small-bumps":1,"fns-with-large-bumps":0,"fns-with-severe-bumps":0,"worst-bump":{"bumps":2,"bump-locs":43,"name":"certificate_managed","start-line":323,"end-line":459},"bumps-by-severity":[{"bumps":2,"bump-locs":43,"name":"certificate_managed","start-line":323,"end-line":459}]},"longest-fn-loc":115,"cohesion":1,"delta":{"active-code-delta":0,"cc-total-delta":0,"nested-depth-delta":0,"n-functions-delta":0},"clone-ratio":0,"fn-args":{"ctors-with-many-args":[],"max-args":8,"n-primitives":0,"fns-with-many-args":[{"name":"crl_managed","start-line":462,"end-line":579,"n-args":8}],"max-ctor-args":0,"n-string-args":0,"mean-args":3.8333333333333335,"max-ctor-arg-name":"<unknown>","n-args":23,"max-arg-name":"crl_managed"},"cc-max":22,"n-clones":0,"congestion":{"authors":0,"fractal-value":0.0},"median-fn-loc":52.0,"cc-max-name":"certificate_managed","cc-total":64},"score":7,"last-month-high-resolution-score":7.3098232073275575,"file-details":{"name":"salt/salt/states/x509.py","resolved":"/Users/andreaskarlsson/Documents/Exjobb/algorithm/test-oracle/repos/salt/salt/states/x509.py","repo-path":"/Users/andreaskarlsson/Documents/Exjobb/algorithm/test-oracle/repos/salt","relative-name":"salt/states/x509.py"},"last-year":0}