{"last-year-high-resolution-score":10.0,"high-resolution-score":10.0,"revision":"5fed7a65a2","calculated":true,"name":"chef/spec/functional/knife/cookbook_delete_spec.rb","last-month":10,"last-month-details":{"name":"chef/spec/functional/knife/cookbook_delete_spec.rb","score":10,"high-resolution-score":10.0,"unbiased-score":10.0,"details":{"cc-mean":1.0,"main-body-cc":0,"lines-in-file":108,"complex-functions":[],"cc-median":1.0,"nested":{"contains-named-nested-functions":true,"nested-complexity-of-interest":[],"max-nested-in-global-scope":1,"max-nested-complexity-depth":0,"max-nested-complexity-depth-name":"<unknown>"},"excess-long-functions":[],"fns-with-duplicated-code":[{"name":"\"when there is only one version of a cookbook\"::\"asks for confirmation, then deletes the cookbook\"","start-line":68,"end-line":80},{"name":"\"when there is only one version of a cookbook\"::\"asks for confirmation before purging\"","start-line":82,"end-line":98}],"complex-conditionals":[],"longest-fn-loc-name":"\"when there are several versions of a cookbook\"::\"deletes all versions of the cookbook when not given the -a flag and the user chooses to delete all\"","n-functions":6,"active-code-size":64,"bumps":{},"longest-fn-loc":13,"cohesion":1,"clone-ratio":0.3333333333333333,"fn-args":{"ctors-with-many-args":[],"max-args":0,"n-primitives":0,"fns-with-many-args":[],"max-ctor-args":0,"n-string-args":0,"mean-args":0.0,"max-ctor-arg-name":"<unknown>","n-args":0,"max-arg-name":"\"when the cookbook doesn't exist\"::\"logs an error and exits\""},"cc-max":1,"n-clones":2,"congestion":{"authors":1,"fractal-value":0.0},"median-fn-loc":12.0,"cc-max-name":"\"when there are several versions of a cookbook\"::\"deletes all versions of the cookbook when not given the -a flag and the user chooses to delete all\"","cc-total":6},"revision":"5fed7a65a2","date":"2014-10-29"},"last-year-details":{"details":{"lines-in-file":108},"revision":"b19b7d0008","date":"2014-01-29"},"unbiased-score":10.0,"details":{"cc-mean":1.0,"main-body-cc":0,"lines-in-file":108,"social":{"owner":"Daniel DeLeo","ownership":0.72,"knowledge-loss":0.0},"complex-functions":[],"cc-median":1.0,"nested":{"contains-named-nested-functions":true,"nested-complexity-of-interest":[],"max-nested-in-global-scope":1,"max-nested-complexity-depth":0,"max-nested-complexity-depth-name":"<unknown>"},"code-comment-match":[{"n-matches":0,"pattern-name":"Detect TODOs"}],"excess-long-functions":[],"fns-with-duplicated-code":[{"name":"\"when there is only one version of a cookbook\"::\"asks for confirmation, then deletes the cookbook\"","start-line":68,"end-line":80},{"name":"\"when there is only one version of a cookbook\"::\"asks for confirmation before purging\"","start-line":82,"end-line":98}],"complex-conditionals":[],"longest-fn-loc-name":"\"when there are several versions of a cookbook\"::\"deletes all versions of the cookbook when not given the -a flag and the user chooses to delete all\"","n-functions":6,"active-code-size":64,"bumps":{},"longest-fn-loc":13,"cohesion":1,"delta":{"active-code-delta":0,"cc-total-delta":0,"nested-depth-delta":0,"n-functions-delta":0},"clone-ratio":0.3333333333333333,"fn-args":{"ctors-with-many-args":[],"max-args":0,"n-primitives":0,"fns-with-many-args":[],"max-ctor-args":0,"n-string-args":0,"mean-args":0.0,"max-ctor-arg-name":"<unknown>","n-args":0,"max-arg-name":"\"when the cookbook doesn't exist\"::\"logs an error and exits\""},"cc-max":1,"n-clones":2,"congestion":{"authors":0,"fractal-value":0.0},"median-fn-loc":12.0,"cc-max-name":"\"when there are several versions of a cookbook\"::\"deletes all versions of the cookbook when not given the -a flag and the user chooses to delete all\"","cc-total":6},"score":10,"last-month-high-resolution-score":10.0,"file-details":{"name":"chef/spec/functional/knife/cookbook_delete_spec.rb","resolved":"/Users/andreaskarlsson/Documents/Exjobb/algorithm/test-oracle/repos/chef/spec/functional/knife/cookbook_delete_spec.rb","repo-path":"/Users/andreaskarlsson/Documents/Exjobb/algorithm/test-oracle/repos/chef","relative-name":"spec/functional/knife/cookbook_delete_spec.rb"},"last-year":10}